decibel/__init__.py
decibel/__main__.py
decibel/cli.py
decibel/context.py
decibel/dsl.py
decibel/flow.py
decibel/host_context.py
decibel/optimizers.py
decibel/runbook.py
decibel/runnable.py
decibel/tasks.py
decibel/ansible/__init__.py
decibel/ansible/tasks.py
pydecibel-0.1.0.dist-info/LICENCE
pydecibel-0.1.0.dist-info/METADATA
pydecibel-0.1.0.dist-info/WHEEL
pydecibel-0.1.0.dist-info/entry_points.txt
pydecibel-0.1.0.dist-info/top_level.txt
pydecibel-0.1.0.dist-info/RECORD
