Metadata-Version: 2.1
Name: pydecibel
Version: 0.1.0
Summary: Turn your infrastructure up to eleven!
Home-page: https://github.com/ArmedGuy/decibel
Author: Johan Jatko
Author-email: armedguy@ludd.ltu.se
Classifier: Programming Language :: Python :: 3
Classifier: License :: OSI Approved :: MIT License
Classifier: Operating System :: OS Independent
Requires-Python: >=3.7
License-File: LICENCE
Requires-Dist: PyYAML (>=5.3.1)
